cpptiff/cpptiff.cpython-311-darwin.so
cpptiff/__init__.py
cpptiff/cpptiffwrappers.py
cpptiff/.dylibs/libcppTiff.dylib
cpptiff/.dylibs/libgomp.1.dylib
cpp_tiff-1.1.3.dist-info/RECORD
cpp_tiff-1.1.3.dist-info/WHEEL
cpp_tiff-1.1.3.dist-info/top_level.txt
cpp_tiff-1.1.3.dist-info/METADATA
