Metadata-Version: 2.1
Name: cpp-tiff
Version: 1.1.3
Summary: Python wrappers for cpp-tiff
Home-page: https://github.com/abcucberkeley/cpp-tiff
Author: Matthew Mueller
Author-email: matthewmueller@berkeley.edu
Classifier: Programming Language :: Python :: 3
Classifier: Operating System :: OS Independent
Requires-Python: >=3.8
Requires-Dist: numpy >=1.20
